tibet_chip/__init__.py
tibet_chip/__main__.py
tibet_chip/classifier.py
tibet_chip/provenance.py
tibet_chip/server.py
tibet_chip-1.0.1.dist-info/METADATA
tibet_chip-1.0.1.dist-info/WHEEL
tibet_chip-1.0.1.dist-info/entry_points.txt
tibet_chip-1.0.1.dist-info/licenses/LICENSE
tibet_chip-1.0.1.dist-info/RECORD
