Metadata-Version: 2.4
Name: tibet-chip
Version: 1.0.1
Summary: TIBET Safety Chip - Hardware-like AI Security at TPM Cost
Project-URL: Homepage, https://humotica.com
Project-URL: Repository, https://github.com/jaspertvdm/tibet-chip
Author-email: Claude & Jasper <info@humotica.com>
License-Expression: AGPL-3.0-or-later
License-File: LICENSE
Keywords: ai-safety,humotica,mcp,prompt-injection,provenance,security,tibet
Classifier: Development Status :: 4 - Beta
Classifier: Intended Audience :: Developers
Classifier: License :: OSI Approved :: GNU Affero General Public License v3
Classifier: Programming Language :: Python :: 3
Classifier: Programming Language :: Python :: 3.10
Classifier: Programming Language :: Python :: 3.11
Classifier: Programming Language :: Python :: 3.12
Classifier: Topic :: Scientific/Engineering :: Artificial Intelligence
Classifier: Topic :: Security
Requires-Python: >=3.10
Requires-Dist: mcp>=1.0.0
